detect_hate_speech/main.py
detect_hate_speech/utils.py
detect_hate_speech-0.1.8.dist-info/LICENSE
detect_hate_speech-0.1.8.dist-info/METADATA
detect_hate_speech-0.1.8.dist-info/WHEEL
detect_hate_speech-0.1.8.dist-info/RECORD
