Metadata-Version: 2.1
Name: detect-hate-speech
Version: 0.1.8
Summary: 
Author: Amanda Nobre
Author-email: amandapnobre@gmail.com
Requires-Python: >=3.7,<4.0
Classifier: Programming Language :: Python :: 3
Classifier: Programming Language :: Python :: 3.7
Classifier: Programming Language :: Python :: 3.8
Classifier: Programming Language :: Python :: 3.9
Classifier: Programming Language :: Python :: 3.10
Classifier: Programming Language :: Python :: 3.11
